damsextractor/__init__.py
damsextractor/ex.py
dams_extractor-0.2.3.dist-info/LICENSE
dams_extractor-0.2.3.dist-info/METADATA
dams_extractor-0.2.3.dist-info/WHEEL
dams_extractor-0.2.3.dist-info/top_level.txt
dams_extractor-0.2.3.dist-info/RECORD
