Metadata-Version: 2.1
Name: dams-extractor
Version: 0.2.3
Summary: A boilerpy3 text extractor wrapper
Author: 
License-File: LICENSE
